pdl_api/__init__.py
pdl_api/models/exceptions.py
pdl_api/models/person.py
pdl_api/models/response.py
pdl_api/person_api.py
pdl_api/py.typed
pdl_api-0.1.2.dist-info/METADATA
pdl_api-0.1.2.dist-info/WHEEL
pdl_api-0.1.2.dist-info/RECORD
